lektor_gae.py
setup.py
lektor_gae.egg-info/PKG-INFO
lektor_gae.egg-info/SOURCES.txt
lektor_gae.egg-info/dependency_links.txt
lektor_gae.egg-info/entry_points.txt
lektor_gae.egg-info/requires.txt
lektor_gae.egg-info/top_level.txt