Metadata-Version: 1.1
Name: lektor-gae
Version: 0.1
Summary: Publishes your Lektor site to Google App Engine.
Home-page: https://github.com/isotherm/lektor-gae/
Author: Kirk Meyer
Author-email: kirk.meyer@alpaxo.com
License: MIT
Platform: any
Classifier: Development Status :: 4 - Beta
Classifier: Environment :: Web Environment
Classifier: Intended Audience :: Developers
Classifier: License :: OSI Approved :: MIT License
Classifier: Operating System :: OS Independent
Classifier: Programming Language :: Python :: 2.7
Classifier: Topic :: Internet :: WWW/HTTP :: Site Management
Classifier: Topic :: Software Development :: Libraries :: Python Modules
